{
  "openapi": "3.0.1",
  "info": {
    "title": "reposicion_pin",
    "version": "1.0"
  },
  "paths": {
    "/api/reposicion-pin": {
      "post": {
        "tags": [
          "ReposicionPin"
        ],
        "requestBody": {
          "content": {
            "application/json": {
              "schema": {
                "$ref": "#/components/schemas/ReposicionPinRequestDto"
              }
            },
            "text/json": {
              "schema": {
                "$ref": "#/components/schemas/ReposicionPinRequestDto"
              }
            },
            "application/*+json": {
              "schema": {
                "$ref": "#/components/schemas/ReposicionPinRequestDto"
              }
            }
          }
        },
        "responses": {
          "200": {
            "description": "OK",
            "content": {
              "text/plain": {
                "schema": {
                  "$ref": "#/components/schemas/ReposicionPinResponseDto"
                }
              },
              "application/json": {
                "schema": {
                  "$ref": "#/components/schemas/ReposicionPinResponseDto"
                }
              },
              "text/json": {
                "schema": {
                  "$ref": "#/components/schemas/ReposicionPinResponseDto"
                }
              }
            }
          }
        }
      }
    }
  },
  "components": {
    "schemas": {
      "ReposicionPinRequestDto": {
        "type": "object",
        "properties": {
          "cif": {
            "type": "string",
            "nullable": true
          },
          "dni": {
            "type": "string",
            "nullable": true
          },
          "cliente": {
            "type": "string",
            "nullable": true
          },
          "metodoEnvio": {
            "type": "integer",
            "format": "int32"
          },
          "telefono": {
            "type": "string",
            "nullable": true
          },
          "operadorTelefono": {
            "type": "string",
            "nullable": true
          },
          "correo": {
            "type": "string",
            "nullable": true
          },
          "ultimosDigitosTC": {
            "type": "string",
            "nullable": true
          },
          "contenidoSMS": {
            "type": "string",
            "nullable": true
          },
          "contenidoCorreo": {
            "type": "string",
            "nullable": true
          }
        },
        "additionalProperties": false
      },
      "ReposicionPinResponseDto": {
        "type": "object",
        "properties": {
          "codigo": {
            "type": "string",
            "nullable": true,
            "readOnly": true
          },
          "descripcion": {
            "type": "string",
            "nullable": true
          }
        },
        "additionalProperties": false
      }
    }
  }
}